evalai/__init__.py
evalai/add_token.py
evalai/challenges.py
evalai/get_token.py
evalai/login.py
evalai/main.py
evalai/set_host.py
evalai/submissions.py
evalai/teams.py
evalai/urls.py
evalai/version.py
evalai/utils/__init__.py
evalai/utils/auth.py
evalai/utils/challenges.py
evalai/utils/common.py
evalai/utils/config.py
evalai/utils/requests.py
evalai/utils/submissions.py
evalai/utils/teams.py
evalai/utils/updates.py
evalai/utils/urls.py
tests/data/__init__.py
tests/data/challenge_response.py
tests/data/submission_response.py
tests/data/teams_response.py
evalai-1.3.18.dist-info/LICENSE
evalai-1.3.18.dist-info/METADATA
evalai-1.3.18.dist-info/WHEEL
evalai-1.3.18.dist-info/entry_points.txt
evalai-1.3.18.dist-info/namespace_packages.txt
evalai-1.3.18.dist-info/top_level.txt
evalai-1.3.18.dist-info/RECORD
